agraphx-2025.12.18.1.dist-info/licenses/LICENSE
agx/__init__.py
agx/py.typed
agx/utilities.py
agx/_internal/__init__.py
agx/_internal/configuration.py
agx/_internal/configuredcode.py
agx/_internal/enumeration.py
agx/_internal/node.py
agx/_internal/topology_code.py
agx/_internal/utilities.py
agx/_internal/known_graphs/rxx_1-2FG.json.gz
agx/_internal/known_graphs/rxx_1-2FG_2-1FG.json.gz
agx/_internal/known_graphs/rxx_1-3FG_1-2FG_1-1FG.json.gz
agx/_internal/known_graphs/rxx_1-3FG_3-1FG.json.gz
agx/_internal/known_graphs/rxx_1-4FG.json.gz
agx/_internal/known_graphs/rxx_1-4FG_1-2FG_2-1FG.json.gz
agx/_internal/known_graphs/rxx_1-4FG_1-3FG_1-1FG.json.gz
agx/_internal/known_graphs/rxx_1-4FG_2-2FG.json.gz
agx/_internal/known_graphs/rxx_1-4FG_4-1FG.json.gz
agx/_internal/known_graphs/rxx_1-5FG_1-2FG_3-1FG.json.gz
agx/_internal/known_graphs/rxx_1-5FG_1-3FG_2-1FG.json.gz
agx/_internal/known_graphs/rxx_1-5FG_1-4FG_1-1FG.json.gz
agx/_internal/known_graphs/rxx_1-5FG_2-2FG_1-1FG.json.gz
agx/_internal/known_graphs/rxx_1-5FG_5-1FG.json.gz
agx/_internal/known_graphs/rxx_10-1FG.json.gz
agx/_internal/known_graphs/rxx_10-2FG.json.gz
agx/_internal/known_graphs/rxx_10-2FG_20-1FG.json
agx/_internal/known_graphs/rxx_10-3FG.json.gz
agx/_internal/known_graphs/rxx_10-4FG.json.gz
agx/_internal/known_graphs/rxx_10-4FG_20-2FG.json
agx/_internal/known_graphs/rxx_10-5FG.json.gz
agx/_internal/known_graphs/rxx_11-2FG.json
agx/_internal/known_graphs/rxx_11-2FG_22-1FG.json
agx/_internal/known_graphs/rxx_12-1FG.json
agx/_internal/known_graphs/rxx_12-2FG_24-1FG.json
agx/_internal/known_graphs/rxx_2-1FG.json.gz
agx/_internal/known_graphs/rxx_2-2FG.json.gz
agx/_internal/known_graphs/rxx_2-2FG_4-1FG.json.gz
agx/_internal/known_graphs/rxx_2-3FG.json.gz
agx/_internal/known_graphs/rxx_2-3FG_1-2FG_4-1FG.json.gz
agx/_internal/known_graphs/rxx_2-3FG_2-2FG_2-1FG.json.gz
agx/_internal/known_graphs/rxx_2-3FG_3-2FG.json.gz
agx/_internal/known_graphs/rxx_2-3FG_6-1FG.json.gz
agx/_internal/known_graphs/rxx_2-4FG.json.gz
agraphx-2025.12.18.1.dist-info/METADATA
agraphx-2025.12.18.1.dist-info/WHEEL
agraphx-2025.12.18.1.dist-info/entry_points.txt
agraphx-2025.12.18.1.dist-info/top_level.txt
agraphx-2025.12.18.1.dist-info/RECORD
