Metadata-Version: 2.4
Name: agraphx
Version: 2025.12.18.1
Maintainer-email: Andrew Tarzia <andrew.tarzia@gmail.com>
Project-URL: github, https://github.com/andrewtarzia/agx
Project-URL: documentation, https://agx.readthedocs.io
Requires-Python: >=3.11
License-File: LICENSE
Requires-Dist: numpy
Requires-Dist: rustworkx
Requires-Dist: networkx
Requires-Dist: scipy
Provides-Extra: dev
Requires-Dist: ruff; extra == "dev"
Requires-Dist: mypy; extra == "dev"
Requires-Dist: pytest<8; extra == "dev"
Requires-Dist: pytest-cov; extra == "dev"
Requires-Dist: sphinx; extra == "dev"
Requires-Dist: sphinx-copybutton; extra == "dev"
Requires-Dist: twine; extra == "dev"
Requires-Dist: sphinx_rtd_theme; extra == "dev"
Requires-Dist: furo; extra == "dev"
Requires-Dist: matplotlib; extra == "dev"
Requires-Dist: moldoc; extra == "dev"
Dynamic: license-file
